psowi/__init__.py
psowi/psowi.py
psowi-1.0.3.dist-info/LICENSE
psowi-1.0.3.dist-info/METADATA
psowi-1.0.3.dist-info/WHEEL
psowi-1.0.3.dist-info/top_level.txt
psowi-1.0.3.dist-info/RECORD
