Metadata-Version: 2.1
Name: psowi
Version: 1.0.3
Summary: Keras Model Weight Initialization By PSO
Home-page: https://github.com/Lanping-Tech/PSOWI
Author: lanping_tech
Author-email: lanping_tech@qq.com
License: UNKNOWN
Platform: UNKNOWN
Classifier: Programming Language :: Python :: 3
Classifier: License :: OSI Approved :: MIT License
Classifier: Operating System :: OS Independent
Requires-Python: >=3.7
License-File: LICENSE
Requires-Dist: numpy
Requires-Dist: tensorflow
Requires-Dist: keras
